klldFN/__init__.py
klldFN/arprint.py
klldFN/client.py
klldFN/clients.py
klldFN/config.py
klldFN/discord.py
klldFN/epicgames.py
klldFN/utils.py
rebootpy/__init__.py
rebootpy/auth.py
rebootpy/avatar.py
rebootpy/client.py
rebootpy/creative.py
rebootpy/enums.py
rebootpy/errors.py
rebootpy/friend.py
rebootpy/http.py
rebootpy/message.py
rebootpy/news.py
rebootpy/party.py
rebootpy/playlist.py
rebootpy/presence.py
rebootpy/stats.py
rebootpy/store.py
rebootpy/typedefs.py
rebootpy/user.py
rebootpy/utils.py
rebootpy/websocket.py
rebootpy/xmpp.py
rebootpy/ext/commands/__init__.py
rebootpy/ext/commands/_types.py
rebootpy/ext/commands/bot.py
rebootpy/ext/commands/cog.py
rebootpy/ext/commands/context.py
rebootpy/ext/commands/converter.py
rebootpy/ext/commands/cooldown.py
rebootpy/ext/commands/core.py
rebootpy/ext/commands/errors.py
rebootpy/ext/commands/help.py
rebootpy/ext/commands/typedefs.py
rebootpy/ext/commands/view.py
klldfn-2.8.12.dist-info/METADATA
klldfn-2.8.12.dist-info/WHEEL
klldfn-2.8.12.dist-info/top_level.txt
klldfn-2.8.12.dist-info/RECORD
